noise/__init__.py
noise/charsets.py
noise/errors.py
noise/noise.py
noise_cipher-0.1.4.dist-info/LICENSE
noise_cipher-0.1.4.dist-info/METADATA
noise_cipher-0.1.4.dist-info/WHEEL
noise_cipher-0.1.4.dist-info/top_level.txt
noise_cipher-0.1.4.dist-info/RECORD
