Metadata-Version: 2.1
Name: noise-cipher
Version: 0.1.4
Summary: A new cipher module
Home-page: https://github.com/DaRealCodeWritten/Noise-Cipher
Author: CodeWritten
Author-email: ytcodew@gmail.com
License: UNKNOWN
Platform: UNKNOWN
Classifier: Programming Language :: Python :: 3
Classifier: License :: OSI Approved :: MIT License
Classifier: Operating System :: OS Independent
Requires-Python: >=3.6
